servicetools/__init__.py
servicetools/lazyactor.py
servicetools/logging_config.py
servicetools/middleware.py
servicetools/testing.py
servicetools/timer.py
python_service_tools-0.5.2.dist-info/LICENSE
python_service_tools-0.5.2.dist-info/METADATA
python_service_tools-0.5.2.dist-info/WHEEL
python_service_tools-0.5.2.dist-info/RECORD
