Metadata-Version: 2.1
Name: python-service-tools
Version: 0.5.2
Summary: Utilities for working with python services.
Home-page: https://github.com/mongodb-labs/python-service-tools
License: Apache-2.0
Author: Alexander Costas
Author-email: alexander.costas@mongodb.com
Requires-Python: >=3.7,<4.0
Classifier: License :: OSI Approved :: Apache Software License
Classifier: Programming Language :: Python :: 3
Classifier: Programming Language :: Python :: 3.7
Classifier: Programming Language :: Python :: 3.8
Classifier: Programming Language :: Python :: 3.9
Classifier: Programming Language :: Python :: 3.10
Classifier: Programming Language :: Python :: 3.11
Requires-Dist: dramatiq[rabbitmq,watch] (>=1.10)
Requires-Dist: pika (>=1.2)
Requires-Dist: python-json-logger (>=0.1)
Requires-Dist: starlette (>=0.13)
Requires-Dist: structlog (>=19)
Requires-Dist: typed-ast (>=1.5.4,<2.0.0)
Project-URL: Repository, https://github.com/mongodb-labs/python-service-tools
